merge_project_diff/__init__.py
merge_project_diff/__main__.py
merge_project_diff/manifest_diff.py
merge_project_diff/merge_project_files.py
merge_project_diff/merge_public.py
merge_project_diff/merge_xml_diff.py
projectdiff-1.0.9.dist-info/LICENSE
projectdiff-1.0.9.dist-info/METADATA
projectdiff-1.0.9.dist-info/WHEEL
projectdiff-1.0.9.dist-info/entry_points.txt
projectdiff-1.0.9.dist-info/top_level.txt
projectdiff-1.0.9.dist-info/RECORD
